parkinglotpuzzle/lot.py
parkinglotpuzzle/rush.txt
parkinglotpuzzle-1.0.2.dist-info/licenses/LICENSE
parkinglotpuzzle-1.0.2.dist-info/METADATA
parkinglotpuzzle-1.0.2.dist-info/WHEEL
parkinglotpuzzle-1.0.2.dist-info/top_level.txt
parkinglotpuzzle-1.0.2.dist-info/RECORD
