Metadata-Version: 2.4
Name: parkinglotpuzzle
Version: 1.0.2
Summary: Library for Rush Hour game
Author-email: Evaldas Visockas <developersediary@gmail.com>
License: GPL-3.0-or-later
Project-URL: Repository, https://github.com/EvalVis/ParkingLot
Requires-Python: >=3.12
License-File: LICENSE
Provides-Extra: dev
Requires-Dist: pytest>=8.3.4; extra == "dev"
Requires-Dist: pytest-cov>=6.1.1; extra == "dev"
Dynamic: license-file
